caesar/__init__.py
caesar/_base_client.py
caesar/_client.py
caesar/_compat.py
caesar/_constants.py
caesar/_exceptions.py
caesar/_files.py
caesar/_models.py
caesar/_qs.py
caesar/_resource.py
caesar/_response.py
caesar/_streaming.py
caesar/_types.py
caesar/_version.py
caesar/pagination.py
caesar/py.typed
caesar/_utils/__init__.py
caesar/_utils/_compat.py
caesar/_utils/_datetime_parse.py
caesar/_utils/_logs.py
caesar/_utils/_proxy.py
caesar/_utils/_reflection.py
caesar/_utils/_resources_proxy.py
caesar/_utils/_streams.py
caesar/_utils/_sync.py
caesar/_utils/_transform.py
caesar/_utils/_typing.py
caesar/_utils/_utils.py
caesar/lib/.keep
caesar/resources/__init__.py
caesar/resources/research/__init__.py
caesar/resources/research/files.py
caesar/resources/research/research.py
caesar/resources/research/results.py
caesar/types/__init__.py
caesar/types/research_create_params.py
caesar/types/research_create_response.py
caesar/types/research_list_params.py
caesar/types/research_list_response.py
caesar/types/research_retrieve_response.py
caesar/types/research/__init__.py
caesar/types/research/file_create_params.py
caesar/types/research/file_create_response.py
caesar/types/research/file_list_params.py
caesar/types/research/file_list_response.py
caesar/types/research/result_retrieve_content_response.py
caesar_data-1.0.0.dist-info/METADATA
caesar_data-1.0.0.dist-info/WHEEL
caesar_data-1.0.0.dist-info/licenses/LICENSE
caesar_data-1.0.0.dist-info/RECORD
